odoo10_addon_base_technical_user-10.0.1.1.0-nspkg.pth
odoo/addons/base_technical_user/README.rst
odoo/addons/base_technical_user/__init__.py
odoo/addons/base_technical_user/__manifest__.py
odoo/addons/base_technical_user/i18n/base_technical_user.pot
odoo/addons/base_technical_user/i18n/de.po
odoo/addons/base_technical_user/i18n/es.po
odoo/addons/base_technical_user/i18n/fr.po
odoo/addons/base_technical_user/i18n/hr.po
odoo/addons/base_technical_user/i18n/it.po
odoo/addons/base_technical_user/i18n/nl_NL.po
odoo/addons/base_technical_user/i18n/pt.po
odoo/addons/base_technical_user/models/__init__.py
odoo/addons/base_technical_user/models/models.py
odoo/addons/base_technical_user/models/res_company.py
odoo/addons/base_technical_user/static/description/icon.png
odoo/addons/base_technical_user/tests/__init__.py
odoo/addons/base_technical_user/tests/test_sudo_tech.py
odoo/addons/base_technical_user/views/res_company_view.xml
odoo10_addon_base_technical_user-10.0.1.1.0.dist-info/METADATA
odoo10_addon_base_technical_user-10.0.1.1.0.dist-info/WHEEL
odoo10_addon_base_technical_user-10.0.1.1.0.dist-info/namespace_packages.txt
odoo10_addon_base_technical_user-10.0.1.1.0.dist-info/top_level.txt
odoo10_addon_base_technical_user-10.0.1.1.0.dist-info/RECORD
