Metadata-Version: 2.1
Name: odoo10-addon-base-technical-user
Version: 10.0.1.1.0
Summary: Add a technical user parameter on the company
Home-page: http://acsone.eu
Author: ACSONE SA/NV, Odoo Community Association (OCA)
Author-email: support@odoo-community.org
License: AGPL-3
Platform: UNKNOWN
Classifier: Programming Language :: Python
Classifier: Framework :: Odoo
Classifier: License :: OSI Approved :: GNU Affero General Public License v3
Requires-Python: ~=2.7
Requires-Dist: odoo (<10.1dev,>=10.0)
